TerminatorBaseCore/LICENSE
TerminatorBaseCore/README.md
TerminatorBaseCore/__init__.py
TerminatorBaseCore/apps.py
TerminatorBaseCore/common/__init__.py
TerminatorBaseCore/common/constant.py
TerminatorBaseCore/common/error_code.py
TerminatorBaseCore/components/__init__.py
TerminatorBaseCore/components/aliyun_util.py
TerminatorBaseCore/components/dynamic_call.py
TerminatorBaseCore/components/import_scan.py
TerminatorBaseCore/components/logger_util.py
TerminatorBaseCore/components/redis_mq.py
TerminatorBaseCore/entity/__init__.py
TerminatorBaseCore/entity/design_patterns.py
TerminatorBaseCore/entity/exception.py
TerminatorBaseCore/entity/message.py
TerminatorBaseCore/entity/response.py
TerminatorBaseCore/middleware/__init__.py
TerminatorBaseCore/middleware/exception_middleware.py
TerminatorBaseCore/middleware/token_middleware.py
TerminatorBaseCore/route/__init__.py
TerminatorBaseCore/route/load_custom_viewsets_from_directory.py
TerminatorBaseCore/route/route.py
TerminatorBaseCore/route/viewset.py
TerminatorBaseCore/service/__init__.py
TerminatorBaseCore/service/authenticated_with_redis.py
TerminatorBaseCore/service/base_compoment_handler.py
TerminatorBaseCore/service/base_service_handler.py
TerminatorBaseCore/utils/__init__.py
TerminatorBaseCore/utils/entity_export_util.py
TerminatorBaseCore/utils/ip_util.py
TerminatorBaseCore/utils/rate_limit_util.py
TerminatorBaseCore/utils/serializer_util.py
TerminatorBaseCore/utils/token_manger.py
terminatorcore-0.1.19.dist-info/METADATA
terminatorcore-0.1.19.dist-info/WHEEL
terminatorcore-0.1.19.dist-info/top_level.txt
terminatorcore-0.1.19.dist-info/RECORD
