Metadata-Version: 2.4
Name: TerminatorCore
Version: 0.1.19
Summary: django增强
Author-email: "bw.song" <tyj003@163.com>
License: MIT
Keywords: Terminator,SONG
Classifier: Programming Language :: Python :: 3
Classifier: License :: OSI Approved :: MIT License
Classifier: Operating System :: OS Independent
Requires-Python: >=3.8
